src/__init__.py
src/app.py
Flask_App_Multi-0.1.7.dist-info/LICENCE
Flask_App_Multi-0.1.7.dist-info/METADATA
Flask_App_Multi-0.1.7.dist-info/WHEEL
Flask_App_Multi-0.1.7.dist-info/top_level.txt
Flask_App_Multi-0.1.7.dist-info/RECORD
